iolite/__init__.py
iolite-25.1.0.dist-info/licenses/LICENSE
iolite-25.1.0.dist-info/METADATA
iolite-25.1.0.dist-info/WHEEL
iolite-25.1.0.dist-info/top_level.txt
iolite-25.1.0.dist-info/RECORD
