Metadata-Version: 2.4
Name: iolite
Version: 25.1.0
Summary: Add your description here
Requires-Python: >=3.8
License-File: LICENSE
Requires-Dist: joblib
Requires-Dist: toml
Requires-Dist: tqdm
Dynamic: license-file
